<Properties StartupConfiguration="{6492EFC8-F387-475A-B783-1F754BDC7DC9}|Default">
  <MonoDevelop.Ide.Workspace ActiveConfiguration="Debug" />
  <MonoDevelop.Ide.ItemProperties.Prosper PreferredExecutionTarget="Android.pixel_5_-_api_33" />
  <Xamarin.Addins.Core.Project ActiveDebugTarget="Android.pixel_5_-_api_33" />
  <MultiItemStartupConfigurations />
  <MonoDevelop.MonoDroid LastDeploySdkVersion="33.0.95" />
  <MonoDevelop.Ide.DebuggingService.PinnedWatches />
  <MonoDevelop.Ide.DebuggingService.Breakpoints>
    <BreakpointStore />
  </MonoDevelop.Ide.DebuggingService.Breakpoints>
  <MonoDevelop.Ide.Workbench ActiveDocument="Repositories/BaseRepository.cs">
    <Files>
      <File FileName="MVVM/Models/Transaction.cs" Line="2" Column="7" />
      <File FileName="MVVM/ViewModels/DashBoardViewModel.cs" Line="1" Column="1" />
      <File FileName="MVVM/Views/AppContainer.xaml" Line="1" Column="1" />
      <File FileName="MVVM/Views/DashboardPage.xaml" Line="1" Column="1" />
      <File FileName="Repositories/BaseRepository.cs" Line="1" Column="1" />
    </Files>
    <Pads>
      <Pad Id="ProjectPad">
        <State name="__root__">
          <Node name="Prosper" expanded="True" selected="True">
            <Node name="Prosper" expanded="True">
              <Node name="MVVM" expanded="True">
                <Node name="Models" expanded="True" />
                <Node name="ViewModels" expanded="True" />
                <Node name="Views" expanded="True" />
              </Node>
              <Node name="Repositories" expanded="True" />
            </Node>
          </Node>
        </State>
      </Pad>
    </Pads>
  </MonoDevelop.Ide.Workbench>
</Properties>